iroh-0.35.0.dist-info/METADATA
iroh-0.35.0.dist-info/WHEEL
iroh/__init__.py
iroh/__init__.pyi
iroh/iroh_ffi.py
iroh/libiroh_ffi.so
iroh/py.typed
iroh-0.35.0.dist-info/RECORD
