Metadata-Version: 2.4
Name: iroh
Version: 0.35.0
Classifier: Development Status :: 3 - Alpha
Classifier: Intended Audience :: Developers
Classifier: Topic :: System :: Networking
Classifier: Programming Language :: Rust
Classifier: Programming Language :: Python :: Implementation :: CPython
Classifier: Programming Language :: Python :: Implementation :: PyPy
Summary: A toolkit for building distributed applications
Home-Page: https://iroh.computer
Author: n0 team
License: MIT OR Apache-2.0
Requires-Python: >=3.7
Project-URL: Source Code, https://github.com/n0-computer/iroh-ffi
